goprolib
